gTTS/__init__.py
gTTS/cache.py
gTTS/models.py
gTTS/tests.py
gTTS/urls.py
gTTS/urls_auth.py
gTTS/views.py
gTTS/migrations/0001_initial.py
gTTS/migrations/__init__.py
gTTS/templatetags/__init__.py
gTTS/templatetags/gTTS.py
Django_Gtts-0.4.dist-info/LICENSE
Django_Gtts-0.4.dist-info/METADATA
Django_Gtts-0.4.dist-info/WHEEL
Django_Gtts-0.4.dist-info/top_level.txt
Django_Gtts-0.4.dist-info/RECORD
